LiamSpiderToolkit/Liam_random.py
LiamSpiderToolkit/Proxy_Pool.py
LiamSpiderToolkit/Spader_nover_jiami_to_sqliit.py
LiamSpiderToolkit/__init__.py
LiamSpiderToolkit/base_knowledge.py
LiamSpiderToolkit/download_file.py
LiamSpiderToolkit/pa_novel_test_active_01.py
LiamSpiderToolkit/tar_file.py
LiamSpiderToolkit/test.py
LiamSpiderToolkit-0.0.20.data/scripts/LiamSpider
LiamSpiderToolkit-0.0.20.dist-info/METADATA
LiamSpiderToolkit-0.0.20.dist-info/WHEEL
LiamSpiderToolkit-0.0.20.dist-info/top_level.txt
LiamSpiderToolkit-0.0.20.dist-info/RECORD
